errator.py
_errator.cpython-38-x86_64-linux-gnu.so
errator-0.4.dist-info/RECORD
errator-0.4.dist-info/LICENSE.txt
errator-0.4.dist-info/WHEEL
errator-0.4.dist-info/top_level.txt
errator-0.4.dist-info/METADATA
