Metadata-Version: 2.1
Name: errator
Version: 0.4
Summary: Errator allows you to create human-readable exception narrations
Home-page: https://github.com/haxsaw/errator
Author: Tom Carroll
Author-email: tcarroll@incisivetech.co.uk
License: MIT
Download-URL: https://github.com/haxsaw/errator/archive/0.4.tar.gz
Keywords: exception,logging,traceback,stacktrace
Platform: UNKNOWN
